sitekicker/__init__.py
sitekicker/__main__.py
sitekicker/entry/entry.py
sitekicker/entry/entry_dir.py
sitekicker/entry/entry_file.py
sitekicker/entry/entry_image.py
sitekicker/entry/entry_tasks.py
sitekicker/entry/entry_template.py
sitekicker/folder/asset_folder.py
sitekicker/folder/enclosure_folder.py
sitekicker/folder/entry_folder.py
sitekicker/folder/template_folder.py
sitekicker/jinja2_filters.py
sitekicker/site.py
sitekicker/site_server.py
sitekicker/site_tasks.py
sitekicker/site_watcher.py
sitekicker/util.py
sitekicker/watermark.py
sitekicker-1.0.6.dist-info/entry_points.txt
sitekicker-1.0.6.dist-info/WHEEL
sitekicker-1.0.6.dist-info/METADATA
sitekicker-1.0.6.dist-info/RECORD
